open_api_framework/__init__.py
open_api_framework/admin.py
open_api_framework/apps.py
open_api_framework/context_processors.py
open_api_framework/py.typed
open_api_framework/utils.py
open_api_framework/conf/__init__.py
open_api_framework/conf/base.py
open_api_framework/conf/utils.py
open_api_framework/management/__init__.py
open_api_framework/management/commands/__init__.py
open_api_framework/management/commands/generate_envvar_docs.py
open_api_framework/static/open_api_framework/css/admin.css
open_api_framework/templates/open_api_framework/env_config.rst
open_api_framework/templates/open_api_framework/admin/base_site.html
open_api_framework/templates/open_api_framework/components/environment.html
open_api_framework/templates/open_api_framework/components/version.html
open_api_framework/templatetags/__init__.py
open_api_framework/templatetags/doc_tags.py
open_api_framework/templatetags/open_api_framework.py
open_api_framework-0.13.2.dist-info/licenses/LICENSE
open_api_framework-0.13.2.dist-info/METADATA
open_api_framework-0.13.2.dist-info/WHEEL
open_api_framework-0.13.2.dist-info/top_level.txt
open_api_framework-0.13.2.dist-info/RECORD
