Metadata-Version: 2.4
Name: open-api-framework
Version: 0.13.2
Summary: A metapackage for registration components, that bundles the dependencies shared between these components and provides generic settings
Author-email: Maykin Media <support@maykinmedia.nl>
License: Copyright © Maykin 2024
Project-URL: Homepage, https://github.com/maykinmedia/open-api-framework
Project-URL: Documentation, http://open-api-framework.readthedocs.io/en/latest/
Project-URL: Bug Tracker, https://github.com/maykinmedia/open-api-framework/issues
Project-URL: Source Code, https://github.com/maykinmedia/open-api-framework
Keywords: metapackage,dependencies,settings
Classifier: Development Status :: 3 - Alpha
Classifier: Framework :: Django
Classifier: Framework :: Django :: 5.2
Classifier: Intended Audience :: Developers
Classifier: Operating System :: Unix
Classifier: Operating System :: MacOS
Classifier: Operating System :: Microsoft :: Windows
Classifier: Programming Language :: Python :: 3.12
Classifier: Topic :: Software Development :: Libraries :: Python Modules
Requires-Python: >=3.12
License-File: LICENSE
Requires-Dist: django>=5.2
Requires-Dist: django-axes>=6.5.1
Requires-Dist: django-jsonform>=2.22.0
Requires-Dist: django-log-outgoing-requests>=0.6.1
Requires-Dist: django-admin-index>=3.1.0
Requires-Dist: djangorestframework>=3.15.2
Requires-Dist: django-filter>=24.2
Requires-Dist: drf-spectacular[sidecar]>=0.27.2
Requires-Dist: mozilla-django-oidc-db>=0.19.0
Requires-Dist: psycopg[binary]>=3.2.9
Requires-Dist: python-dotenv>=1.0.0
Requires-Dist: python-decouple>=3.8
Requires-Dist: requests>=2.32.3
Requires-Dist: sentry-sdk>=2.11.0
Requires-Dist: elastic-apm>=6.22.0
Requires-Dist: maykin-2fa>=1.0.1
Requires-Dist: django-setup-configuration>=0.1.0
Requires-Dist: django-sessionprofile>=3.0.0
Requires-Dist: django-upgrade-check>=1.1.0
Provides-Extra: tests
Requires-Dist: pytest; extra == "tests"
Requires-Dist: pytest-django; extra == "tests"
Requires-Dist: pytest-env; extra == "tests"
Requires-Dist: tox; extra == "tests"
Requires-Dist: ruff; extra == "tests"
Requires-Dist: factory-boy; extra == "tests"
Requires-Dist: django-rosetta; extra == "tests"
Requires-Dist: django-webtest; extra == "tests"
Provides-Extra: coverage
Requires-Dist: pytest-cov; extra == "coverage"
Provides-Extra: docs
Requires-Dist: sphinx; extra == "docs"
Requires-Dist: sphinx-rtd-theme; extra == "docs"
Provides-Extra: release
Requires-Dist: bump-my-version; extra == "release"
Requires-Dist: twine; extra == "release"
Provides-Extra: celery
Requires-Dist: celery>=5.4.0; extra == "celery"
Requires-Dist: flower>=2.0.1; extra == "celery"
Provides-Extra: cors
Requires-Dist: django-cors-headers>=4.4.0; extra == "cors"
Provides-Extra: markup
Requires-Dist: django-markup>=1.8.1; extra == "markup"
Provides-Extra: geo
Requires-Dist: djangorestframework-gis>=1.0; extra == "geo"
Provides-Extra: csp
Requires-Dist: django-csp>=4.0; extra == "csp"
Provides-Extra: commonground
Requires-Dist: commonground-api-common>=2.7.0; extra == "commonground"
Provides-Extra: inclusions
Requires-Dist: djangorestframework-inclusions>=1.2.0; extra == "inclusions"
Provides-Extra: sanitization
Requires-Dist: bleach>=6.1.0; extra == "sanitization"
Provides-Extra: server
Requires-Dist: uwsgi>=2.0.23; extra == "server"
Provides-Extra: redis
Requires-Dist: django-redis>=5.4.0; extra == "redis"
Provides-Extra: structlog
Requires-Dist: structlog>=25.4.0; extra == "structlog"
Requires-Dist: django-structlog>=9.1.1; extra == "structlog"
Provides-Extra: structlog-celery
Requires-Dist: structlog>=25.4.0; extra == "structlog-celery"
Requires-Dist: django-structlog[celery]>=9.1.1; extra == "structlog-celery"
Dynamic: license-file
